jupyterlab_markdown_viewer_toc_fix/__init__.py
jupyterlab_markdown_viewer_toc_fix/_version.py
jupyterlab_markdown_viewer_toc_fix-1.0.15.data/data/share/jupyter/labextensions/jupyterlab_markdown_viewer_toc_fix/package.json
jupyterlab_markdown_viewer_toc_fix-1.0.15.data/data/share/jupyter/labextensions/jupyterlab_markdown_viewer_toc_fix/static/509.957f1f068291bb49d0c5.js
jupyterlab_markdown_viewer_toc_fix-1.0.15.data/data/share/jupyter/labextensions/jupyterlab_markdown_viewer_toc_fix/static/728.c89ae43ea05743404154.js
jupyterlab_markdown_viewer_toc_fix-1.0.15.data/data/share/jupyter/labextensions/jupyterlab_markdown_viewer_toc_fix/static/remoteEntry.f0af161d4d2b73d175bc.js
jupyterlab_markdown_viewer_toc_fix-1.0.15.data/data/share/jupyter/labextensions/jupyterlab_markdown_viewer_toc_fix/static/style.js
jupyterlab_markdown_viewer_toc_fix-1.0.15.data/data/share/jupyter/labextensions/jupyterlab_markdown_viewer_toc_fix/static/third-party-licenses.json
jupyterlab_markdown_viewer_toc_fix-1.0.15.data/data/share/jupyter/labextensions/jupyterlab_markdown_viewer_toc_fix/install.json
jupyterlab_markdown_viewer_toc_fix-1.0.15.dist-info/METADATA
jupyterlab_markdown_viewer_toc_fix-1.0.15.dist-info/WHEEL
jupyterlab_markdown_viewer_toc_fix-1.0.15.dist-info/licenses/LICENSE
jupyterlab_markdown_viewer_toc_fix-1.0.15.dist-info/RECORD
